LNPLab/__init__.py
LNPLab/cheminfo/__init__.py
LNPLab/cheminfo/fin/__init__.py
LNPLab/cheminfo/fin/tda.py
LNPLab/cheminfo/fin/vec.py
LNPLab/cheminfo/prop/__init__.py
LNPLab/cheminfo/prop/cal.py
LNPLab/cheminfo/prop/dln.py
LNPLab-0.0.3.dist-info/LICENSE
LNPLab-0.0.3.dist-info/METADATA
LNPLab-0.0.3.dist-info/WHEEL
LNPLab-0.0.3.dist-info/top_level.txt
LNPLab-0.0.3.dist-info/RECORD
