Metadata-Version: 2.1
Name: LNPLab
Version: 0.0.3
Summary: Utils for LNP Solution and Clients
Home-page: https://github.com/wosaKim/LNPLab
Author: william
Author-email: william@lnpsolution.com
Keywords: Deep Learning Model Evaluation,Smart Banch
Classifier: Programming Language :: Python :: 3.6
Classifier: Programming Language :: Python :: 3.7
Classifier: Programming Language :: Python :: 3.8
Classifier: Programming Language :: Python :: 3.9
Requires-Python: >=3.6
License-File: LICENSE
Requires-Dist: tqdm
Requires-Dist: pandas
Requires-Dist: scikit-learn
Requires-Dist: rdkit
